{"ref":"1b7ca14a-b015-43f1-b76d-eab82b9cf8dd","content":"{\"version\":2,\"machineId\":\"809b1232-7d5c-48cc-82e6-d06fafb7e316\",\"content\":\"{\\\"windows\\\":\\\"// Place your key bindings in this file to override the defaults\\\\r\\\\n[\\\\r\\\\n    {\\\\r\\\\n        \\\\\\\"key\\\\\\\": \\\\\\\"ctrl+shift+s\\\\\\\",\\\\r\\\\n        \\\\\\\"command\\\\\\\": \\\\\\\"saveAll\\\\\\\"\\\\r\\\\n    },\\\\r\\\\n    {\\\\r\\\\n        \\\\\\\"key\\\\\\\": \\\\\\\"ctrl+k s\\\\\\\",\\\\r\\\\n        \\\\\\\"command\\\\\\\": \\\\\\\"-saveAll\\\\\\\"\\\\r\\\\n    },\\\\r\\\\n    {\\\\r\\\\n        \\\\\\\"key\\\\\\\": \\\\\\\"ctrl+k s\\\\\\\",\\\\r\\\\n        \\\\\\\"command\\\\\\\": \\\\\\\"workbench.action.files.saveAs\\\\\\\"\\\\r\\\\n    },\\\\r\\\\n    {\\\\r\\\\n        \\\\\\\"key\\\\\\\": \\\\\\\"ctrl+shift+s\\\\\\\",\\\\r\\\\n        \\\\\\\"command\\\\\\\": \\\\\\\"-workbench.action.files.saveAs\\\\\\\"\\\\r\\\\n    },\\\\r\\\\n    {\\\\r\\\\n        \\\\\\\"key\\\\\\\": \\\\\\\"ctrl+k s\\\\\\\",\\\\r\\\\n        \\\\\\\"command\\\\\\\": \\\\\\\"workbench.action.files.saveLocalFile\\\\\\\",\\\\r\\\\n        \\\\\\\"when\\\\\\\": \\\\\\\"remoteFileDialogVisible\\\\\\\"\\\\r\\\\n    },\\\\r\\\\n    {\\\\r\\\\n        \\\\\\\"key\\\\\\\": \\\\\\\"ctrl+shift+s\\\\\\\",\\\\r\\\\n        \\\\\\\"command\\\\\\\": \\\\\\\"-workbench.action.files.saveLocalFile\\\\\\\",\\\\r\\\\n        \\\\\\\"when\\\\\\\": \\\\\\\"remoteFileDialogVisible\\\\\\\"\\\\r\\\\n    },\\\\r\\\\n    {\\\\r\\\\n        \\\\\\\"key\\\\\\\": \\\\\\\"ctrl+shift+l\\\\\\\",\\\\r\\\\n        \\\\\\\"command\\\\\\\": \\\\\\\"editor.action.insertSnippet\\\\\\\",\\\\r\\\\n        \\\\\\\"when\\\\\\\": \\\\\\\"editorTextFocus\\\\\\\",\\\\r\\\\n        \\\\\\\"args\\\\\\\": {\\\\r\\\\n          \\\\\\\"snippet\\\\\\\": \\\\\\\"console.log('${TM_SELECTED_TEXT}$1:--> ', ${TM_SELECTED_TEXT}$1)$2;\\\\\\\"\\\\r\\\\n        }\\\\r\\\\n      }\\\\r\\\\n]\\\\r\\\\n//----------------------------------------------------------------------\\\",\\\"all\\\":\\\"// Place your key bindings in this file to override the defaults\\\\r\\\\n[\\\\r\\\\n    {\\\\r\\\\n        \\\\\\\"key\\\\\\\": \\\\\\\"ctrl+shift+s\\\\\\\",\\\\r\\\\n        \\\\\\\"command\\\\\\\": \\\\\\\"saveAll\\\\\\\"\\\\r\\\\n    },\\\\r\\\\n    {\\\\r\\\\n        \\\\\\\"key\\\\\\\": \\\\\\\"ctrl+k s\\\\\\\",\\\\r\\\\n        \\\\\\\"command\\\\\\\": \\\\\\\"-saveAll\\\\\\\"\\\\r\\\\n    },\\\\r\\\\n    {\\\\r\\\\n        \\\\\\\"key\\\\\\\": \\\\\\\"ctrl+k s\\\\\\\",\\\\r\\\\n        \\\\\\\"command\\\\\\\": \\\\\\\"workbench.action.files.saveAs\\\\\\\"\\\\r\\\\n    },\\\\r\\\\n    {\\\\r\\\\n        \\\\\\\"key\\\\\\\": \\\\\\\"ctrl+shift+s\\\\\\\",\\\\r\\\\n        \\\\\\\"command\\\\\\\": \\\\\\\"-workbench.action.files.saveAs\\\\\\\"\\\\r\\\\n    },\\\\r\\\\n    {\\\\r\\\\n        \\\\\\\"key\\\\\\\": \\\\\\\"ctrl+k s\\\\\\\",\\\\r\\\\n        \\\\\\\"command\\\\\\\": \\\\\\\"workbench.action.files.saveLocalFile\\\\\\\",\\\\r\\\\n        \\\\\\\"when\\\\\\\": \\\\\\\"remoteFileDialogVisible\\\\\\\"\\\\r\\\\n    },\\\\r\\\\n    {\\\\r\\\\n        \\\\\\\"key\\\\\\\": \\\\\\\"ctrl+shift+s\\\\\\\",\\\\r\\\\n        \\\\\\\"command\\\\\\\": \\\\\\\"-workbench.action.files.saveLocalFile\\\\\\\",\\\\r\\\\n        \\\\\\\"when\\\\\\\": \\\\\\\"remoteFileDialogVisible\\\\\\\"\\\\r\\\\n    },\\\\r\\\\n    {\\\\r\\\\n        \\\\\\\"key\\\\\\\": \\\\\\\"ctrl+shift+l\\\\\\\",\\\\r\\\\n        \\\\\\\"command\\\\\\\": \\\\\\\"editor.action.insertSnippet\\\\\\\",\\\\r\\\\n        \\\\\\\"when\\\\\\\": \\\\\\\"editorTextFocus\\\\\\\",\\\\r\\\\n        \\\\\\\"args\\\\\\\": {\\\\r\\\\n          \\\\\\\"snippet\\\\\\\": \\\\\\\"console.log('${TM_SELECTED_TEXT}$1:--> ', ${TM_SELECTED_TEXT}$1)$2;\\\\\\\"\\\\r\\\\n        }\\\\r\\\\n      }\\\\r\\\\n]\\\\r\\\\n//----------------------------------------------------------------------\\\"}\"}","platformSpecific":true}